openics/__init__.py
openics/core/__init__.py
openics/core/camera.py
openics/core/math.py
openics/visions/__init__.py
openics/visions/garbage.py
openics-0.1.6.1.dist-info/DESCRIPTION.rst
openics-0.1.6.1.dist-info/METADATA
openics-0.1.6.1.dist-info/RECORD
openics-0.1.6.1.dist-info/WHEEL
openics-0.1.6.1.dist-info/metadata.json
openics-0.1.6.1.dist-info/top_level.txt
