Metadata-Version: 2.0
Name: openics
Version: 0.1.6.1
Summary: iCreativeFactor's library for autonomous system.
Home-page: https://github.com/iCreativeFactor/openics
Author: iCreativeFactor
Author-email: adadesions@gmail.com
License: UNKNOWN
Project-URL: Bug Reports, https://github.com/iCreativeFactor/openics/issues
Project-URL: Source, https://github.com/iCreativeFactor/openics
Keywords: openics,machine learning,vision,ai,icreativefactor,adafactor,icreativesystem,open_ics
Platform: UNKNOWN
Classifier: Development Status :: 3 - Alpha
Classifier: Intended Audience :: Developers
Classifier: Topic :: Software Development :: Build Tools
Classifier: License :: OSI Approved :: MIT License
Classifier: Programming Language :: Python :: 2.7
Classifier: Programming Language :: Python :: 3
Classifier: Programming Language :: Python :: 3.4
Classifier: Programming Language :: Python :: 3.5
Classifier: Programming Language :: Python :: 3.6
Requires-Python: >=2.7
Provides-Extra: test
Provides-Extra: dev
Requires-Dist: numpy
Requires-Dist: opencv-python
Provides-Extra: dev
Requires-Dist: check-manifest; extra == 'dev'
Provides-Extra: test
Requires-Dist: coverage; extra == 'test'
